{
    "Mu50_OR_OldMu100_OR_TkMu100_PtBins": {
        "pt_ratio": {
            "pt:[44.0,48.0]": {
                "value": 7.553469181060791, 
                "error": 0.10245761578386306
            }, 
            "pt:[700.0,1200.0]": {
                "value": 1.0083500146865845, 
                "error": 0.16089677519981097
            }, 
            "pt:[48.0,50.0]": {
                "value": 3.146005630493164, 
                "error": 0.019655857743867033
            }, 
            "pt:[56.0,60.0]": {
                "value": 0.9643447995185852, 
                "error": 0.0008916948333760842
            }, 
            "pt:[60.0,120.0]": {
                "value": 0.9722719788551331, 
                "error": 0.0007773347822411071
            }, 
            "pt:[120.0,200.0]": {
                "value": 0.9800987839698792, 
                "error": 0.006560884524424901
            }, 
            "pt:[300.0,500.0]": {
                "value": 0.9735516905784607, 
                "error": 0.013324087136071132
            }, 
            "pt:[52.0,56.0]": {
                "value": 0.9466856122016907, 
                "error": 0.0006772268253024725
            }, 
            "pt:[2.0,44.0]": {
                "value": 7.2055511474609375, 
                "error": 0.2028159954939631
            }, 
            "pt:[50.0,52.0]": {
                "value": 0.8233547806739807, 
                "error": 0.001057593840681233
            }, 
            "pt:[200.0,300.0]": {
                "value": 0.974439263343811, 
                "error": 0.006917368460244953
            }, 
            "pt:[500.0,700.0]": {
                "value": 0.9066586494445801, 
                "error": 0.052984808112129134
            }
        }
    }, 
    "Mu50_OR_OldMu100_OR_TkMu100_EtaBins": {
        "eta_ratio": {
            "eta:[-0.2,0.2]": {
                "value": 0.9812501668930054, 
                "error": 0.0008951991075075912
            }, 
            "eta:[-2.4,-2.1]": {
                "value": 0.9403966665267944, 
                "error": 0.003796279715342885
            }, 
            "eta:[0.3,0.9]": {
                "value": 0.9700567126274109, 
                "error": 0.0008545786662497213
            }, 
            "eta:[-0.9,-0.3]": {
                "value": 0.9785141944885254, 
                "error": 0.0007628993737902438
            }, 
            "eta:[0.2,0.3]": {
                "value": 0.9591519832611084, 
                "error": 0.00342484318170199
            }, 
            "eta:[0.9,1.2]": {
                "value": 0.950234055519104, 
                "error": 0.0013267621022577897
            }, 
            "eta:[-1.2,-0.9]": {
                "value": 0.9579704403877258, 
                "error": 0.0013365161778445247
            }, 
            "eta:[2.1,2.4]": {
                "value": 0.9255697727203369, 
                "error": 0.0036614561574940968
            }, 
            "eta:[-1.6,-1.2]": {
                "value": 0.943682074546814, 
                "error": 0.00146451038488766
            }, 
            "eta:[1.2,1.6]": {
                "value": 0.9276590347290039, 
                "error": 0.0015253849790834318
            }, 
            "eta:[-2.1,-1.6]": {
                "value": 0.9758569002151489, 
                "error": 0.00191561371625311
            }, 
            "eta:[-0.3,-0.2]": {
                "value": 0.9549254775047302, 
                "error": 0.003190240398041901
            }, 
            "eta:[1.6,2.1]": {
                "value": 0.9773529171943665, 
                "error": 0.0018150315251039967
            }
        }
    }, 
    "IsoMu24_EtaBins": {
        "eta_ratio": {
            "eta:[-0.2,0.2]": {
                "value": 0.982696533203125, 
                "error": 0.00035434830577195446
            }, 
            "eta:[-2.4,-2.1]": {
                "value": 1.0128568410873413, 
                "error": 0.0013608987591382875
            }, 
            "eta:[0.3,0.9]": {
                "value": 0.9716013073921204, 
                "error": 0.00033911651404538166
            }, 
            "eta:[-0.9,-0.3]": {
                "value": 0.9799882173538208, 
                "error": 0.0003294543015377786
            }, 
            "eta:[0.2,0.3]": {
                "value": 0.9599559307098389, 
                "error": 0.00107574529070464
            }, 
            "eta:[0.9,1.2]": {
                "value": 0.9560092687606812, 
                "error": 0.0005474433634857154
            }, 
            "eta:[-1.2,-0.9]": {
                "value": 0.9608476161956787, 
                "error": 0.0005438727508102248
            }, 
            "eta:[2.1,2.4]": {
                "value": 0.9914278388023376, 
                "error": 0.0013342209634740958
            }, 
            "eta:[-1.6,-1.2]": {
                "value": 0.9526621699333191, 
                "error": 0.000609073405765124
            }, 
            "eta:[1.2,1.6]": {
                "value": 0.9411579370498657, 
                "error": 0.0006379119092333161
            }, 
            "eta:[-2.1,-1.6]": {
                "value": 1.0000392198562622, 
                "error": 0.0007561246086181605
            }, 
            "eta:[-0.3,-0.2]": {
                "value": 0.9612147808074951, 
                "error": 0.0010790384279746143
            }, 
            "eta:[1.6,2.1]": {
                "value": 1.006019115447998, 
                "error": 0.000727548453156528
            }
        }
    }, 
    "Mu50_OR_OldMu100_OR_TkMu100_VtxBins": {
        "tag_nVertices_ratio": {
            "tag:[30.5,32.5]": {
                "value": 0.959619402885437, 
                "error": 0.0015971769971555685
            }, 
            "tag:[46.5,48.5]": {
                "value": 0.9569465517997742, 
                "error": 0.0047199157285581815
            }, 
            "tag:[28.5,30.5]": {
                "value": 0.9584577679634094, 
                "error": 0.001474170220323751
            }, 
            "tag:[44.5,46.5]": {
                "value": 0.9563943147659302, 
                "error": 0.003985154972527718
            }, 
            "tag:[6.5,8.5]": {
                "value": 0.9691599011421204, 
                "error": 0.005872359600936642
            }, 
            "tag:[14.5,16.5]": {
                "value": 0.9662997722625732, 
                "error": 0.0017855694754983086
            }, 
            "tag:[50.5,52.5]": {
                "value": 0.9607478380203247, 
                "error": 0.00897942838114355
            }, 
            "tag:[24.5,26.5]": {
                "value": 0.9610700011253357, 
                "error": 0.0014718778719114828
            }, 
            "tag:[34.5,36.5]": {
                "value": 0.9580833911895752, 
                "error": 0.002058151457370165
            }, 
            "tag:[8.5,10.5]": {
                "value": 0.9672395586967468, 
                "error": 0.0036867691580541734
            }, 
            "tag:[18.5,20.5]": {
                "value": 0.966231107711792, 
                "error": 0.0015964129996545405
            }, 
            "tag:[16.5,18.5]": {
                "value": 0.9663001894950867, 
                "error": 0.001677626814822781
            }, 
            "tag:[56.5,58.5]": {
                "value": 0.9739635586738586, 
                "error": 0.013229433301094605
            }, 
            "tag:[32.5,34.5]": {
                "value": 0.9599510431289673, 
                "error": 0.0018645425851755088
            }, 
            "tag:[48.5,50.5]": {
                "value": 0.9594923257827759, 
                "error": 0.005903752899796773
            }, 
            "tag:[22.5,24.5]": {
                "value": 0.962673008441925, 
                "error": 0.0013753599055685525
            }, 
            "tag:[52.5,54.5]": {
                "value": 0.9642638564109802, 
                "error": 0.009155209782850551
            }, 
            "tag:[42.5,44.5]": {
                "value": 0.9589511156082153, 
                "error": 0.0035447317340000432
            }, 
            "tag:[38.5,40.5]": {
                "value": 0.9545733332633972, 
                "error": 0.002423460376477135
            }, 
            "tag:[2.5,4.5]": {
                "value": 0.9529197216033936, 
                "error": 0.01848117639249102
            }, 
            "tag:[12.5,14.5]": {
                "value": 0.9661341309547424, 
                "error": 0.0022391191049140197
            }, 
            "tag:[0.5,2.5]": {
                "value": 0.9864803552627563, 
                "error": 0.02692339807392198
            }, 
            "tag:[40.5,42.5]": {
                "value": 0.9563680291175842, 
                "error": 0.002783004762252398
            }, 
            "tag:[54.5,56.5]": {
                "value": 0.9493229985237122, 
                "error": 0.010311527626588567
            }, 
            "tag:[20.5,22.5]": {
                "value": 0.9616022706031799, 
                "error": 0.0014494785422379027
            }, 
            "tag:[10.5,12.5]": {
                "value": 0.9650311470031738, 
                "error": 0.00249751339457192
            }, 
            "tag:[26.5,28.5]": {
                "value": 0.962273895740509, 
                "error": 0.0015039293461348402
            }, 
            "tag:[58.5,60.5]": {
                "value": 0.9738726019859314, 
                "error": 0.014521101079484748
            }, 
            "tag:[36.5,38.5]": {
                "value": 0.9561681747436523, 
                "error": 0.0020900945848419446
            }, 
            "tag:[4.5,6.5]": {
                "value": 0.977106511592865, 
                "error": 0.010776596987928296
            }
        }
    }, 
    "IsoMu24_VtxBins": {
        "tag_nVertices_ratio": {
            "tag:[30.5,32.5]": {
                "value": 0.9699748158454895, 
                "error": 0.0006164926184239426
            }, 
            "tag:[46.5,48.5]": {
                "value": 0.9692665338516235, 
                "error": 0.002024930718454837
            }, 
            "tag:[28.5,30.5]": {
                "value": 0.970018208026886, 
                "error": 0.0005943105566297525
            }, 
            "tag:[44.5,46.5]": {
                "value": 0.9676273465156555, 
                "error": 0.0016205581092613123
            }, 
            "tag:[6.5,8.5]": {
                "value": 0.9798802137374878, 
                "error": 0.003370583085534334
            }, 
            "tag:[14.5,16.5]": {
                "value": 0.9764160513877869, 
                "error": 0.0007241674264983848
            }, 
            "tag:[50.5,52.5]": {
                "value": 0.9722698926925659, 
                "error": 0.0028572438823646117
            }, 
            "tag:[24.5,26.5]": {
                "value": 0.973711371421814, 
                "error": 0.0005455976183437396
            }, 
            "tag:[34.5,36.5]": {
                "value": 0.9696510434150696, 
                "error": 0.0007331191905868702
            }, 
            "tag:[8.5,10.5]": {
                "value": 0.9809836149215698, 
                "error": 0.0014867860912042325
            }, 
            "tag:[18.5,20.5]": {
                "value": 0.9751865267753601, 
                "error": 0.0006033254876251526
            }, 
            "tag:[16.5,18.5]": {
                "value": 0.9759739637374878, 
                "error": 0.0006427557844732708
            }, 
            "tag:[56.5,58.5]": {
                "value": 0.9596203565597534, 
                "error": 0.004651595574609696
            }, 
            "tag:[32.5,34.5]": {
                "value": 0.9712903499603271, 
                "error": 0.0006862790426340915
            }, 
            "tag:[48.5,50.5]": {
                "value": 0.9680010676383972, 
                "error": 0.0026099836513999346
            }, 
            "tag:[22.5,24.5]": {
                "value": 0.9740415811538696, 
                "error": 0.0005535440853301077
            }, 
            "tag:[52.5,54.5]": {
                "value": 0.9774089455604553, 
                "error": 0.0036255529524650116
            }, 
            "tag:[42.5,44.5]": {
                "value": 0.9691958427429199, 
                "error": 0.0014458808503489166
            }, 
            "tag:[38.5,40.5]": {
                "value": 0.9684549570083618, 
                "error": 0.0009672714581647637
            }, 
            "tag:[2.5,4.5]": {
                "value": 0.9859718084335327, 
                "error": 0.007154807804688312
            }, 
            "tag:[12.5,14.5]": {
                "value": 0.9806861877441406, 
                "error": 0.0008395934389578836
            }, 
            "tag:[0.5,2.5]": {
                "value": 1.0224390029907227, 
                "error": 0.01349231818883064
            }, 
            "tag:[40.5,42.5]": {
                "value": 0.9670873880386353, 
                "error": 0.0011512497855180924
            }, 
            "tag:[54.5,56.5]": {
                "value": 0.9605958461761475, 
                "error": 0.005133909907684809
            }, 
            "tag:[20.5,22.5]": {
                "value": 0.9746260643005371, 
                "error": 0.000565880607894553
            }, 
            "tag:[10.5,12.5]": {
                "value": 0.9783288240432739, 
                "error": 0.0010758386446574238
            }, 
            "tag:[26.5,28.5]": {
                "value": 0.9718334674835205, 
                "error": 0.0005643905007441452
            }, 
            "tag:[58.5,60.5]": {
                "value": 0.9697694778442383, 
                "error": 0.006025864465654457
            }, 
            "tag:[36.5,38.5]": {
                "value": 0.9708711504936218, 
                "error": 0.0008591354658010084
            }, 
            "tag:[4.5,6.5]": {
                "value": 0.9798364639282227, 
                "error": 0.0031420714038192404
            }
        }
    }, 
    "IsoMu24_PtEtaBins": {
        "pt_abseta_ratio": {
            "pt:[200.0,300.0]": {
                "abseta:[0.0,0.9]": {
                    "value": 0.9618107080459595, 
                    "error": 0.009773176203468284
                }, 
                "abseta:[1.2,2.1]": {
                    "value": 0.9664002060890198, 
                    "error": 0.013544845337768405
                }, 
                "abseta:[2.1,2.4]": {
                    "value": 1.0520998239517212, 
                    "error": 0.060249727567463836
                }, 
                "abseta:[0.9,1.2]": {
                    "value": 0.9241194128990173, 
                    "error": 0.015169083903528799
                }
            }, 
            "pt:[30.0,40.0]": {
                "abseta:[0.0,0.9]": {
                    "value": 0.975592315196991, 
                    "error": 0.00031872621144061623
                }, 
                "abseta:[1.2,2.1]": {
                    "value": 0.9729108214378357, 
                    "error": 0.0005944767156764873
                }, 
                "abseta:[2.1,2.4]": {
                    "value": 0.9956144094467163, 
                    "error": 0.0015296210351467183
                }, 
                "abseta:[0.9,1.2]": {
                    "value": 0.9566571712493896, 
                    "error": 0.0006708285943719556
                }
            }, 
            "pt:[26.0,30.0]": {
                "abseta:[0.0,0.9]": {
                    "value": 0.9698455929756165, 
                    "error": 0.0010120757292996
                }, 
                "abseta:[1.2,2.1]": {
                    "value": 0.968589186668396, 
                    "error": 0.0018701847960642965
                }, 
                "abseta:[2.1,2.4]": {
                    "value": 0.9627935886383057, 
                    "error": 0.004382902498295945
                }, 
                "abseta:[0.9,1.2]": {
                    "value": 0.9473601579666138, 
                    "error": 0.0026605589393644997
                }
            }, 
            "pt:[60.0,120.0]": {
                "abseta:[0.0,0.9]": {
                    "value": 0.9751762747764587, 
                    "error": 0.0007756378280095542
                }, 
                "abseta:[1.2,2.1]": {
                    "value": 0.9760234951972961, 
                    "error": 0.0015792332041304968
                }, 
                "abseta:[2.1,2.4]": {
                    "value": 1.0227495431900024, 
                    "error": 0.00440261244408997
                }, 
                "abseta:[0.9,1.2]": {
                    "value": 0.9579103589057922, 
                    "error": 0.0014809662707288677
                }
            }, 
            "pt:[120.0,200.0]": {
                "abseta:[0.0,0.9]": {
                    "value": 0.9631842374801636, 
                    "error": 0.007316778130414942
                }, 
                "abseta:[1.2,2.1]": {
                    "value": 0.9758266806602478, 
                    "error": 0.005378610626394391
                }, 
                "abseta:[2.1,2.4]": {
                    "value": 0.9898489713668823, 
                    "error": 0.020848792719231315
                }, 
                "abseta:[0.9,1.2]": {
                    "value": 0.9551054835319519, 
                    "error": 0.005692228714507397
                }
            }, 
            "pt:[300.0,1200.0]": {
                "abseta:[0.0,0.9]": {
                    "value": 0.9548403024673462, 
                    "error": 0.016451181688483828
                }, 
                "abseta:[1.2,2.1]": {
                    "value": 0.9373623132705688, 
                    "error": 0.04598159411753204
                }, 
                "abseta:[2.1,2.4]": {
                    "value": 1.0252991914749146, 
                    "error": 0.13944500536299353
                }, 
                "abseta:[0.9,1.2]": {
                    "value": 0.9619218111038208, 
                    "error": 0.03259915768284723
                }
            }, 
            "pt:[50.0,60.0]": {
                "abseta:[0.0,0.9]": {
                    "value": 0.9760636687278748, 
                    "error": 0.0005508165687868658
                }, 
                "abseta:[1.2,2.1]": {
                    "value": 0.9756057262420654, 
                    "error": 0.0008655240854720868
                }, 
                "abseta:[2.1,2.4]": {
                    "value": 1.0090028047561646, 
                    "error": 0.0025268757242192814
                }, 
                "abseta:[0.9,1.2]": {
                    "value": 0.9599884152412415, 
                    "error": 0.0009307770260844335
                }
            }, 
            "pt:[40.0,50.0]": {
                "abseta:[0.0,0.9]": {
                    "value": 0.976597249507904, 
                    "error": 0.00023558002679306228
                }, 
                "abseta:[1.2,2.1]": {
                    "value": 0.9738205671310425, 
                    "error": 0.00039546840102962016
                }, 
                "abseta:[2.1,2.4]": {
                    "value": 1.0102187395095825, 
                    "error": 0.0011657069729020927
                }, 
                "abseta:[0.9,1.2]": {
                    "value": 0.9598886966705322, 
                    "error": 0.0004398361111910652
                }
            }
        }, 
        "abseta_pt_ratio": {
            "abseta:[0.0,0.9]": {
                "pt:[200.0,300.0]": {
                    "value": 0.9618107080459595, 
                    "error": 0.009773176203468284
                }, 
                "pt:[30.0,40.0]": {
                    "value": 0.975592315196991, 
                    "error": 0.00031872621144061623
                }, 
                "pt:[26.0,30.0]": {
                    "value": 0.9698455929756165, 
                    "error": 0.0010120757292996
                }, 
                "pt:[60.0,120.0]": {
                    "value": 0.9751762747764587, 
                    "error": 0.0007756378280095542
                }, 
                "pt:[120.0,200.0]": {
                    "value": 0.9631842374801636, 
                    "error": 0.007316778130414942
                }, 
                "pt:[300.0,1200.0]": {
                    "value": 0.9548403024673462, 
                    "error": 0.016451181688483828
                }, 
                "pt:[50.0,60.0]": {
                    "value": 0.9760636687278748, 
                    "error": 0.0005508165687868658
                }, 
                "pt:[40.0,50.0]": {
                    "value": 0.976597249507904, 
                    "error": 0.00023558002679306228
                }
            }, 
            "abseta:[1.2,2.1]": {
                "pt:[200.0,300.0]": {
                    "value": 0.9664002060890198, 
                    "error": 0.013544845337768405
                }, 
                "pt:[30.0,40.0]": {
                    "value": 0.9729108214378357, 
                    "error": 0.0005944767156764873
                }, 
                "pt:[26.0,30.0]": {
                    "value": 0.968589186668396, 
                    "error": 0.0018701847960642965
                }, 
                "pt:[60.0,120.0]": {
                    "value": 0.9760234951972961, 
                    "error": 0.0015792332041304968
                }, 
                "pt:[120.0,200.0]": {
                    "value": 0.9758266806602478, 
                    "error": 0.005378610626394391
                }, 
                "pt:[300.0,1200.0]": {
                    "value": 0.9373623132705688, 
                    "error": 0.04598159411753204
                }, 
                "pt:[50.0,60.0]": {
                    "value": 0.9756057262420654, 
                    "error": 0.0008655240854720868
                }, 
                "pt:[40.0,50.0]": {
                    "value": 0.9738205671310425, 
                    "error": 0.00039546840102962016
                }
            }, 
            "abseta:[2.1,2.4]": {
                "pt:[200.0,300.0]": {
                    "value": 1.0520998239517212, 
                    "error": 0.060249727567463836
                }, 
                "pt:[30.0,40.0]": {
                    "value": 0.9956144094467163, 
                    "error": 0.0015296210351467183
                }, 
                "pt:[26.0,30.0]": {
                    "value": 0.9627935886383057, 
                    "error": 0.004382902498295945
                }, 
                "pt:[60.0,120.0]": {
                    "value": 1.0227495431900024, 
                    "error": 0.00440261244408997
                }, 
                "pt:[120.0,200.0]": {
                    "value": 0.9898489713668823, 
                    "error": 0.020848792719231315
                }, 
                "pt:[300.0,1200.0]": {
                    "value": 1.0252991914749146, 
                    "error": 0.13944500536299353
                }, 
                "pt:[50.0,60.0]": {
                    "value": 1.0090028047561646, 
                    "error": 0.0025268757242192814
                }, 
                "pt:[40.0,50.0]": {
                    "value": 1.0102187395095825, 
                    "error": 0.0011657069729020927
                }
            }, 
            "abseta:[0.9,1.2]": {
                "pt:[200.0,300.0]": {
                    "value": 0.9241194128990173, 
                    "error": 0.015169083903528799
                }, 
                "pt:[30.0,40.0]": {
                    "value": 0.9566571712493896, 
                    "error": 0.0006708285943719556
                }, 
                "pt:[26.0,30.0]": {
                    "value": 0.9473601579666138, 
                    "error": 0.0026605589393644997
                }, 
                "pt:[60.0,120.0]": {
                    "value": 0.9579103589057922, 
                    "error": 0.0014809662707288677
                }, 
                "pt:[120.0,200.0]": {
                    "value": 0.9551054835319519, 
                    "error": 0.005692228714507397
                }, 
                "pt:[300.0,1200.0]": {
                    "value": 0.9619218111038208, 
                    "error": 0.03259915768284723
                }, 
                "pt:[50.0,60.0]": {
                    "value": 0.9599884152412415, 
                    "error": 0.0009307770260844335
                }, 
                "pt:[40.0,50.0]": {
                    "value": 0.9598886966705322, 
                    "error": 0.0004398361111910652
                }
            }
        }
    }, 
    "IsoMu24_PtBins": {
        "pt_ratio": {
            "pt:[22.0,24.0]": {
                "value": 2.302414655685425, 
                "error": 0.0535842532010239
            }, 
            "pt:[18.0,22.0]": {
                "value": 3.925374746322632, 
                "error": 0.6450044091739324
            }, 
            "pt:[300.0,500.0]": {
                "value": 0.9588667154312134, 
                "error": 0.013832913366000068
            }, 
            "pt:[200.0,300.0]": {
                "value": 0.9596779346466064, 
                "error": 0.007235364336813376
            }, 
            "pt:[30.0,40.0]": {
                "value": 0.9728277325630188, 
                "error": 0.00027899525128267585
            }, 
            "pt:[26.0,30.0]": {
                "value": 0.9651920199394226, 
                "error": 0.0009068198942804095
            }, 
            "pt:[60.0,120.0]": {
                "value": 0.9739181399345398, 
                "error": 0.0006937431515618043
            }, 
            "pt:[120.0,200.0]": {
                "value": 0.9686936736106873, 
                "error": 0.0028586046185027267
            }, 
            "pt:[24.0,26.0]": {
                "value": 0.909139096736908, 
                "error": 0.0018994614949283523
            }, 
            "pt:[700.0,1200.0]": {
                "value": 1.121712327003479, 
                "error": 0.17379484842738624
            }, 
            "pt:[2.0,18.0]": {
                "value": 1596114432.0, 
                "error": 6.641861733603028e+16
            }, 
            "pt:[50.0,60.0]": {
                "value": 0.9754810929298401, 
                "error": 0.0004414725344668283
            }, 
            "pt:[500.0,700.0]": {
                "value": 0.8511354327201843, 
                "error": 0.05789005488913219
            }, 
            "pt:[40.0,50.0]": {
                "value": 0.9750906229019165, 
                "error": 0.00019650972533126235
            }
        }
    }, 
    "Mu50_OR_OldMu100_OR_TkMu100_PtEtaBins": {
        "pt_abseta_ratio": {
            "pt:[56.0,60.0]": {
                "abseta:[0.0,0.9]": {
                    "value": 0.9754047393798828, 
                    "error": 0.0010612572164018714
                }, 
                "abseta:[1.2,2.1]": {
                    "value": 0.9586570262908936, 
                    "error": 0.0018093632118872736
                }, 
                "abseta:[2.1,2.4]": {
                    "value": 0.9392232894897461, 
                    "error": 0.005626567656966793
                }, 
                "abseta:[0.9,1.2]": {
                    "value": 0.955184817314148, 
                    "error": 0.0018850033362236658
                }
            }, 
            "pt:[60.0,120.0]": {
                "abseta:[0.0,0.9]": {
                    "value": 0.97603440284729, 
                    "error": 0.0007892283088512151
                }, 
                "abseta:[1.2,2.1]": {
                    "value": 0.972029447555542, 
                    "error": 0.001293369184660823
                }, 
                "abseta:[2.1,2.4]": {
                    "value": 0.9945183992385864, 
                    "error": 0.004299392577517116
                }, 
                "abseta:[0.9,1.2]": {
                    "value": 0.9559249877929688, 
                    "error": 0.0016174694456493014
                }
            }, 
            "pt:[120.0,200.0]": {
                "abseta:[0.0,0.9]": {
                    "value": 0.9723413586616516, 
                    "error": 0.004275734883372312
                }, 
                "abseta:[1.2,2.1]": {
                    "value": 1.0008764266967773, 
                    "error": 0.005226604729646838
                }, 
                "abseta:[2.1,2.4]": {
                    "value": 0.9988738894462585, 
                    "error": 0.019012518199503146
                }, 
                "abseta:[0.9,1.2]": {
                    "value": 0.9703147411346436, 
                    "error": 0.0049541074926030175
                }
            }, 
            "pt:[52.0,56.0]": {
                "abseta:[0.0,0.9]": {
                    "value": 0.9719552397727966, 
                    "error": 0.0007687727929495992
                }, 
                "abseta:[1.2,2.1]": {
                    "value": 0.9287911057472229, 
                    "error": 0.0013373303957795602
                }, 
                "abseta:[2.1,2.4]": {
                    "value": 0.8518246412277222, 
                    "error": 0.004239345989901938
                }, 
                "abseta:[0.9,1.2]": {
                    "value": 0.9496673941612244, 
                    "error": 0.0013967398353934236
                }
            }, 
            "pt:[200.0,300.0]": {
                "abseta:[0.0,0.9]": {
                    "value": 0.9774544835090637, 
                    "error": 0.008630919668192695
                }, 
                "abseta:[1.2,2.1]": {
                    "value": 0.9897539019584656, 
                    "error": 0.012579714800476545
                }, 
                "abseta:[2.1,2.4]": {
                    "value": 0.9882077574729919, 
                    "error": 0.041840389675511826
                }, 
                "abseta:[0.9,1.2]": {
                    "value": 0.9324970245361328, 
                    "error": 0.015219110860167527
                }
            }, 
            "pt:[300.0,1200.0]": {
                "abseta:[0.0,0.9]": {
                    "value": 0.9655165672302246, 
                    "error": 0.016329908314898046
                }, 
                "abseta:[1.2,2.1]": {
                    "value": 0.9853987693786621, 
                    "error": 0.02683358235162388
                }, 
                "abseta:[2.1,2.4]": {
                    "value": 0.910197377204895, 
                    "error": 0.15314475826545706
                }, 
                "abseta:[0.9,1.2]": {
                    "value": 0.949926495552063, 
                    "error": 0.0325701804860575
                }
            }
        }, 
        "abseta_pt_ratio": {
            "abseta:[0.0,0.9]": {
                "pt:[56.0,60.0]": {
                    "value": 0.9754047393798828, 
                    "error": 0.0010612572164018714
                }, 
                "pt:[60.0,120.0]": {
                    "value": 0.97603440284729, 
                    "error": 0.0007892283088512151
                }, 
                "pt:[120.0,200.0]": {
                    "value": 0.9723413586616516, 
                    "error": 0.004275734883372312
                }, 
                "pt:[52.0,56.0]": {
                    "value": 0.9719552397727966, 
                    "error": 0.0007687727929495992
                }, 
                "pt:[200.0,300.0]": {
                    "value": 0.9774544835090637, 
                    "error": 0.008630919668192695
                }, 
                "pt:[300.0,1200.0]": {
                    "value": 0.9655165672302246, 
                    "error": 0.016329908314898046
                }
            }, 
            "abseta:[1.2,2.1]": {
                "pt:[56.0,60.0]": {
                    "value": 0.9586570262908936, 
                    "error": 0.0018093632118872736
                }, 
                "pt:[60.0,120.0]": {
                    "value": 0.972029447555542, 
                    "error": 0.001293369184660823
                }, 
                "pt:[120.0,200.0]": {
                    "value": 1.0008764266967773, 
                    "error": 0.005226604729646838
                }, 
                "pt:[52.0,56.0]": {
                    "value": 0.9287911057472229, 
                    "error": 0.0013373303957795602
                }, 
                "pt:[200.0,300.0]": {
                    "value": 0.9897539019584656, 
                    "error": 0.012579714800476545
                }, 
                "pt:[300.0,1200.0]": {
                    "value": 0.9853987693786621, 
                    "error": 0.02683358235162388
                }
            }, 
            "abseta:[2.1,2.4]": {
                "pt:[56.0,60.0]": {
                    "value": 0.9392232894897461, 
                    "error": 0.005626567656966793
                }, 
                "pt:[60.0,120.0]": {
                    "value": 0.9945183992385864, 
                    "error": 0.004299392577517116
                }, 
                "pt:[120.0,200.0]": {
                    "value": 0.9988738894462585, 
                    "error": 0.019012518199503146
                }, 
                "pt:[52.0,56.0]": {
                    "value": 0.8518246412277222, 
                    "error": 0.004239345989901938
                }, 
                "pt:[200.0,300.0]": {
                    "value": 0.9882077574729919, 
                    "error": 0.041840389675511826
                }, 
                "pt:[300.0,1200.0]": {
                    "value": 0.910197377204895, 
                    "error": 0.15314475826545706
                }
            }, 
            "abseta:[0.9,1.2]": {
                "pt:[56.0,60.0]": {
                    "value": 0.955184817314148, 
                    "error": 0.0018850033362236658
                }, 
                "pt:[60.0,120.0]": {
                    "value": 0.9559249877929688, 
                    "error": 0.0016174694456493014
                }, 
                "pt:[120.0,200.0]": {
                    "value": 0.9703147411346436, 
                    "error": 0.0049541074926030175
                }, 
                "pt:[52.0,56.0]": {
                    "value": 0.9496673941612244, 
                    "error": 0.0013967398353934236
                }, 
                "pt:[200.0,300.0]": {
                    "value": 0.9324970245361328, 
                    "error": 0.015219110860167527
                }, 
                "pt:[300.0,1200.0]": {
                    "value": 0.949926495552063, 
                    "error": 0.0325701804860575
                }
            }
        }
    }
}